ZhonggouGaishanJiyouDaimaDeSheji2nd/README.md
ZhonggouGaishanJiyouDaimaDeSheji2nd/__init__.py
ZhonggouGaishanJiyouDaimaDeSheji2nd/__main__.py
ZhonggouGaishanJiyouDaimaDeSheji2nd/file.epub
ZhonggouGaishanJiyouDaimaDeSheji2nd/index.html
ZhonggouGaishanJiyouDaimaDeSheji2nd/css/__init__.py
ZhonggouGaishanJiyouDaimaDeSheji2nd/css/annotations.css
ZhonggouGaishanJiyouDaimaDeSheji2nd/css/main.css
ZhonggouGaishanJiyouDaimaDeSheji2nd/css/normalize.css
ZhonggouGaishanJiyouDaimaDeSheji2nd/css/popup.css
ZhonggouGaishanJiyouDaimaDeSheji2nd/font/__init__.py
ZhonggouGaishanJiyouDaimaDeSheji2nd/font/fontello.eot
ZhonggouGaishanJiyouDaimaDeSheji2nd/font/fontello.svg
ZhonggouGaishanJiyouDaimaDeSheji2nd/font/fontello.ttf
ZhonggouGaishanJiyouDaimaDeSheji2nd/font/fontello.woff
ZhonggouGaishanJiyouDaimaDeSheji2nd/img/__init__.py
ZhonggouGaishanJiyouDaimaDeSheji2nd/img/annotator-glyph-sprite.png
ZhonggouGaishanJiyouDaimaDeSheji2nd/img/annotator-icon-sprite.png
ZhonggouGaishanJiyouDaimaDeSheji2nd/img/apple-touch-icon.png
ZhonggouGaishanJiyouDaimaDeSheji2nd/img/cancelfullscreen.png
ZhonggouGaishanJiyouDaimaDeSheji2nd/img/close.png
ZhonggouGaishanJiyouDaimaDeSheji2nd/img/fullscreen.png
ZhonggouGaishanJiyouDaimaDeSheji2nd/img/loader.gif
ZhonggouGaishanJiyouDaimaDeSheji2nd/img/menu-icon.png
ZhonggouGaishanJiyouDaimaDeSheji2nd/img/save.png
ZhonggouGaishanJiyouDaimaDeSheji2nd/img/saved.png
ZhonggouGaishanJiyouDaimaDeSheji2nd/img/settings-s.png
ZhonggouGaishanJiyouDaimaDeSheji2nd/img/settings.png
ZhonggouGaishanJiyouDaimaDeSheji2nd/img/star.png
ZhonggouGaishanJiyouDaimaDeSheji2nd/js/__init__.py
ZhonggouGaishanJiyouDaimaDeSheji2nd/js/epub.js
ZhonggouGaishanJiyouDaimaDeSheji2nd/js/epub.min.js
ZhonggouGaishanJiyouDaimaDeSheji2nd/js/epub.min.map
ZhonggouGaishanJiyouDaimaDeSheji2nd/js/hooks.min.js
ZhonggouGaishanJiyouDaimaDeSheji2nd/js/hooks.min.map
ZhonggouGaishanJiyouDaimaDeSheji2nd/js/reader.js
ZhonggouGaishanJiyouDaimaDeSheji2nd/js/reader.js.map
ZhonggouGaishanJiyouDaimaDeSheji2nd/js/reader.min.js
zhonggou_gaishan_jiyou_daima_de_sheji_2nd-2024.3.5.0.dist-info/METADATA
zhonggou_gaishan_jiyou_daima_de_sheji_2nd-2024.3.5.0.dist-info/WHEEL
zhonggou_gaishan_jiyou_daima_de_sheji_2nd-2024.3.5.0.dist-info/entry_points.txt
zhonggou_gaishan_jiyou_daima_de_sheji_2nd-2024.3.5.0.dist-info/top_level.txt
zhonggou_gaishan_jiyou_daima_de_sheji_2nd-2024.3.5.0.dist-info/RECORD
